geomltoolkits/__init__.py
geomltoolkits/__version__.py
geomltoolkits/utils.py
geomltoolkits/downloader/__init__.py
geomltoolkits/downloader/osm.py
geomltoolkits/downloader/tms.py
geomltoolkits/regularizer/__init__.py
geomltoolkits/regularizer/app.py
geomltoolkits/regularizer/orthogonalize.py
geomltoolkits-0.4.2.dist-info/METADATA
geomltoolkits-0.4.2.dist-info/WHEEL
geomltoolkits-0.4.2.dist-info/entry_points.txt
geomltoolkits-0.4.2.dist-info/RECORD
