Metadata-Version: 2.4
Name: geomltoolkits
Version: 0.4.2
Summary: Toolkits for Geospatial Machine Learning
Author-email: kshitijrajsharma <skshitizraj@gmail.com>
License: MIT
Requires-Python: >=3.9
Requires-Dist: aiohttp>=3.10.11
Requires-Dist: geopandas>=0.13.2
Requires-Dist: ipykernel>=6.30.0
Requires-Dist: mercantile>=1.2.1
Requires-Dist: pillow>=9.1.0
Requires-Dist: rasterio>=1.3.11
Requires-Dist: shapely>=1.8.0
Requires-Dist: tqdm>=4.67.0
